universalgreetings/hello.py
universal_greetings-0.7.0.dist-info/METADATA
universal_greetings-0.7.0.dist-info/WHEEL
universal_greetings-0.7.0.dist-info/RECORD
